README.rst
setup.py
hitchsmtp/__init__.py
hitchsmtp/service.py
hitchsmtp/smtp.py
hitchsmtp/smtperrors.py
hitchsmtp.egg-info/PKG-INFO
hitchsmtp.egg-info/SOURCES.txt
hitchsmtp.egg-info/dependency_links.txt
hitchsmtp.egg-info/entry_points.txt
hitchsmtp.egg-info/not-zip-safe
hitchsmtp.egg-info/requires.txt
hitchsmtp.egg-info/top_level.txt